menchero_multiperiod_attribution.py
manchero_method-0.1.3.dist-info/licenses/LICENSE
manchero_method-0.1.3.dist-info/METADATA
manchero_method-0.1.3.dist-info/WHEEL
manchero_method-0.1.3.dist-info/top_level.txt
manchero_method-0.1.3.dist-info/RECORD
