Metadata-Version: 2.4
Name: manchero-method
Version: 0.1.3
Summary: Menchero multiperiod performance attribution calculations at a sector and stock level
Author-email: Differential Capital Data Science Team <info@differential.co.za>
License: MIT License
Project-URL: Source Code, https://github.com/differentialcapital/menchero-multiperiod-attributions
Project-URL: Documentation, https://github.com/differentialcapital/menchero-multiperiod-attributions/blob/main/README.md
Keywords: menchero,performance,finance,attribution
Classifier: Programming Language :: Python :: 3
Classifier: License :: OSI Approved :: MIT License
Classifier: Operating System :: OS Independent
Requires-Python: >=3.7
License-File: LICENSE
Requires-Dist: pandas>=1.2
Requires-Dist: numpy>=1.18
Dynamic: license-file
